ai_logmaster/__init__.py
ai_logmaster/agent.py
ai_logmaster/analyzer.py
ai_logmaster/cli.py
ai_logmaster/config/__init__.py
ai_logmaster/config/config.yaml.example
ai_logmaster/core/__init__.py
ai_logmaster/core/agent.py
ai_logmaster/core/agentic_agent.py
ai_logmaster/core/analyzer.py
ai_logmaster/core/classifier.py
ai_logmaster/core/doc_fetcher.py
ai_logmaster/core/llm_client.py
ai_logmaster/core/tools.py
ai_logmaster-1.0.2.dist-info/licenses/LICENSE
ai_logmaster-1.0.2.dist-info/METADATA
ai_logmaster-1.0.2.dist-info/WHEEL
ai_logmaster-1.0.2.dist-info/entry_points.txt
ai_logmaster-1.0.2.dist-info/top_level.txt
ai_logmaster-1.0.2.dist-info/RECORD
