Metadata-Version: 2.4
Name: ai-logmaster
Version: 1.0.2
Summary: Smart error analysis tool with AI-powered solutions
Home-page: https://github.com/Divodude/ai-logmaster
Author: Divyansh
Author-email: ry604492@gmail.com
Classifier: Development Status :: 4 - Beta
Classifier: Intended Audience :: Developers
Classifier: Topic :: Software Development :: Debuggers
Classifier: License :: OSI Approved :: MIT License
Classifier: Programming Language :: Python :: 3
Classifier: Programming Language :: Python :: 3.8
Classifier: Programming Language :: Python :: 3.9
Classifier: Programming Language :: Python :: 3.10
Classifier: Programming Language :: Python :: 3.11
Requires-Python: >=3.8
License-File: LICENSE
Requires-Dist: langchain>=1.0.0
Requires-Dist: langchain-community>=0.4.0
Requires-Dist: langchain-core>=1.2.0
Requires-Dist: langchain-openai>=1.0.0
Requires-Dist: langgraph>=1.0.0
Requires-Dist: duckduckgo-search>=8.0.0
Requires-Dist: pyyaml>=6.0
Requires-Dist: python-dotenv>=1.0.0
Requires-Dist: requests>=2.32.0
Provides-Extra: rag
Requires-Dist: faiss-cpu>=1.13.0; extra == "rag"
Requires-Dist: beautifulsoup4>=4.12.0; extra == "rag"
Requires-Dist: lxml>=6.0.0; extra == "rag"
Provides-Extra: dev
Requires-Dist: pytest>=7.0.0; extra == "dev"
Requires-Dist: black>=23.0.0; extra == "dev"
Requires-Dist: flake8>=6.0.0; extra == "dev"
Dynamic: author
Dynamic: author-email
Dynamic: classifier
Dynamic: description
Dynamic: description-content-type
Dynamic: home-page
Dynamic: license-file
Dynamic: provides-extra
Dynamic: requires-dist
Dynamic: requires-python
Dynamic: summary
